{
  "indexes": [
    {
      "collectionGroup": "meetings",
      "queryScope": "COLLECTION",
      "fields": [
        { "fieldPath": "createdBy", "order": "ASCENDING" },
        { "fieldPath": "createdAt", "order": "DESCENDING" }
      ]
    },
    {
      "collectionGroup": "offers",
      "queryScope": "COLLECTION",
      "fields": [
        { "fieldPath": "to", "order": "ASCENDING" },
        { "fieldPath": "timestamp", "order": "DESCENDING" }
      ]
    },
    {
      "collectionGroup": "answers",
      "queryScope": "COLLECTION",
      "fields": [
        { "fieldPath": "to", "order": "ASCENDING" },
        { "fieldPath": "timestamp", "order": "DESCENDING" }
      ]
    },
    {
      "collectionGroup": "candidates",
      "queryScope": "COLLECTION",
      "fields": [
        { "fieldPath": "to", "order": "ASCENDING" },
        { "fieldPath": "timestamp", "order": "DESCENDING" }
      ]
    }
  ],
  "fieldOverrides": []
}